{"test":[
    
{"name":"Computer Table","details":"ކޮމްޕިއުޓަރ މޭޒު އަޅިކުލައިގެ 24x18.5 އިންޗި","cat_no":"2.4","ceiling":0.1,"price":800,"qty":1,"duration":13,"sap_no":"B15-2010-02-18-01","vendors": [{"name":"Asters","price":1339,"details":""},{"name":"Fahamas","price":1060,"details":""},{"name":"Fast Supply Point","price":1050,"details":""}], "resercher": {"title": "އ. ކ. އޮފިސަރ","name": "ޙުސައިން ޝަރީފް"},"sg": {"title": "ކައުންސިލް އެގްޒެކެޓިވް","name": "މުޙައްމަދު ރަބީޢު"},"date":"22/12/2022"},
{"name":"Vaccum Cleaner","details":"ކްލިޔަރމެޝިން ވެކިޔުމްކްލީނަރ CV-SC22 (2200W)","cat_no":"2.1","ceiling":0.1,"price":2000,"qty":2,"duration":5,"sap_no":"B15-2017-03-01-39","vendors": [{"name":"Asters","price":1999,"details":""},{"name":"Asters","price":1636.79,"details":""},{"name":"Evercute","price":1950,"details":""}], "resercher": {"title": "އ. ކ. އޮފިސަރ","name": "ޙުސައިން ޝަރީފް"},"sg": {"title": "ކައުންސިލް އެގްޒެކެޓިވް","name": "މުޙައްމަދު ރަބީޢު"},"date":"22/12/2022"},
{"name":"Lights / bulbs","details":"އިމަޖެންސީ ލައިޓް 2 ފޫޓްގެ (ހޮޅިބުރި ތަންމަތި ހިމެނޭ)","cat_no":"1.3","ceiling":0.1,"price":180,"qty":5,"duration":12,"sap_no":"B15-2011-02-39-01","vendors": [{"name":"Veligaa","price":371,"details":""},{"name":"TepCon","price":100,"details":""},{"name":"101 Gadgets","price":195,"details":""}], "resercher": {"title": "އ. ކ. އޮފިސަރ","name": "ޙުސައިން ޝަރީފް"},"sg": {"title": "ކައުންސިލް އެގްޒެކެޓިވް","name": "މުޙައްމަދު ރަބީޢު"},"date":"22/12/2022"},
{"name":"Lights / bulbs","details":"އިމަޖެންސީލައިޓް(90ލެޑްގެ)","cat_no":"1.3","ceiling":0.1,"price":375,"qty":3,"duration":8,"sap_no":"B15-2015-03-01-26","vendors": [{"name":"Veligaa","price":371,"details":""},{"name":"TepCon","price":100,"details":""},{"name":"101 Gadgets","price":195,"details":""}], "resercher": {"title": "އ. ކ. އޮފިސަރ","name": "ޙުސައިން ޝަރީފް"},"sg": {"title": "ކައުންސިލް އެގްޒެކެޓިވް","name": "މުޙައްމަދު ރަބީޢު"},"date":"22/12/2022"},
{"name":"Air conditioner","details":"އެއަރ ކަންޑިޝަނަރ","cat_no":"2.1","ceiling":0.1,"price":15000,"qty":4,"duration":8,"sap_no":"B15-2014-04-09-11","vendors": [{"name":"Asters","price":5699.1,"details":""},{"name":"RefCool","price":9381,"details":""},{"name":"e-Life","price":5999,"details":""}], "resercher": {"title": "އ. ކ. އޮފިސަރ","name": "ޙުސައިން ޝަރީފް"},"sg": {"title": "ކައުންސިލް އެގްޒެކެޓިވް","name": "މުޙައްމަދު ރަބީޢު"},"date":"22/12/2022"},
{"name":"Air conditioner","details":"އެއަރ ކަންޑިޝަނަރ (LG.CX12CX1200BTU) ލައިފްސްގޫޑްއިންޑޯ","cat_no":"2.1","ceiling":0.1,"price":15000,"qty":4,"duration":8,"sap_no":"B15-2015-03-01-16","vendors": [{"name":"Asters","price":5699.1,"details":""},{"name":"RefCool","price":9381,"details":""},{"name":"e-Life","price":5999,"details":""}], "resercher": {"title": "އ. ކ. އޮފިސަރ","name": "ޙުސައިން ޝަރީފް"},"sg": {"title": "ކައުންސިލް އެގްޒެކެޓިވް","name": "މުޙައްމަދު ރަބީޢު"},"date":"22/12/2022"},
{"name":"Air conditioner","details":"އެއަރ ކަންޑިޝަނަރ (LG.CX12CX1200BTU) ލައިފްސްގޫޑްއިންޑޯ","cat_no":"2.1","ceiling":0.1,"price":15000,"qty":4,"duration":8,"sap_no":"B15-2015-03-01-17","vendors": [{"name":"Asters","price":5699.1,"details":""},{"name":"RefCool","price":9381,"details":""},{"name":"e-Life","price":5999,"details":""}], "resercher": {"title": "އ. ކ. އޮފިސަރ","name": "ޙުސައިން ޝަރީފް"},"sg": {"title": "ކައުންސިލް އެގްޒެކެޓިވް","name": "މުޙައްމަދު ރަބީޢު"},"date":"22/12/2022"},
{"name":"Air conditioner","details":"އެއަރ ކަންޑިޝަނަރ (LG.CX12CX1200BTU) ލައިފްސްގޫޑްއިންޑޯ","cat_no":"2.1","ceiling":0.1,"price":15000,"qty":4,"duration":8,"sap_no":"B15-2015-03-01-18","vendors": [{"name":"Asters","price":5699.1,"details":""},{"name":"RefCool","price":9381,"details":""},{"name":"e-Life","price":5999,"details":""}], "resercher": {"title": "އ. ކ. އޮފިސަރ","name": "ޙުސައިން ޝަރީފް"},"sg": {"title": "ކައުންސިލް އެގްޒެކެޓިވް","name": "މުޙައްމަދު ރަބީޢު"},"date":"22/12/2022"},
{"name":"Air conditioner","details":"އެއަރ ކަންޑިޝަނަރ (RAS.CX18CX1800BTU) ހިޓާޗީ","cat_no":"2.1","ceiling":0.1,"price":19657.87,"qty":2,"duration":11,"sap_no":"B15-2012-04-09-08","vendors": [{"name":"Asters","price":7299,"details":""},{"name":"RefCool","price":10399,"details":""},{"name":"e-Life","price":8399,"details":""}], "resercher": {"title": "އ. ކ. އޮފިސަރ","name": "ޙުސައިން ޝަރީފް"},"sg": {"title": "ކައުންސިލް އެގްޒެކެޓިވް","name": "މުޙައްމަދު ރަބީޢު"},"date":"22/12/2022"},
{"name":"Air conditioner","details":"އެއަރ ކަންޑިޝަނަރ (RAS.CX18CX1800BTU) ހިޓާޗީ","cat_no":"2.1","ceiling":0.1,"price":19657.87,"qty":2,"duration":11,"sap_no":"B15-2012-04-09-09","vendors": [{"name":"Asters","price":7299,"details":""},{"name":"RefCool","price":10399,"details":""},{"name":"e-Life","price":8399,"details":""}], "resercher": {"title": "އ. ކ. އޮފިސަރ","name": "ޙުސައިން ޝަރީފް"},"sg": {"title": "ކައުންސިލް އެގްޒެކެޓިވް","name": "މުޙައްމަދު ރަބީޢު"},"date":"22/12/2022"},
{"name":"Amplifier","details":"އެމްޕްލިފަޔަރ SA30  SAJ2002.0085085","cat_no":"2.3","ceiling":0.5,"price":2000,"qty":2,"duration":12,"sap_no":"B15-2011-04-31-02","vendors": [{"name":"komercos","price":1063.6716,"details":""},{"name":"e-indysurplus","price":1445.625,"details":""},{"name":"Pyle Store","price":1649.3232,"details":""}], "resercher": {"title": "އ. ކ. އޮފިސަރ","name": "ޙުސައިން ޝަރީފް"},"sg": {"title": "ކައުންސިލް އެގްޒެކެޓިވް","name": "މުޙައްމަދު ރަބީޢު"},"date":"22/12/2022"},
{"name":"Amplifier","details":"އެމްޕްލިފަޔަރ TOA 11370919 A-1031LH","cat_no":"2.3","ceiling":0.5,"price":2000,"qty":2,"duration":12,"sap_no":"B15-2011-04-31-04","vendors": [{"name":"komercos","price":1063.6716,"details":""},{"name":"e-indysurplus","price":1445.625,"details":""},{"name":"Pyle Store","price":1649.3232,"details":""}], "resercher": {"title": "އ. ކ. އޮފިސަރ","name": "ޙުސައިން ޝަރީފް"},"sg": {"title": "ކައުންސިލް އެގްޒެކެޓިވް","name": "މުޙައްމަދު ރަބީޢު"},"date":"22/12/2022"},
{"name":"Executive Chair","details":"އެގްޒެކްޓިވް ޗެއަރ ހައިބެކް ކަޅުކުލައިގެ","cat_no":"1.1","ceiling":0.05,"price":1500,"qty":5,"duration":13,"sap_no":"B15-2010-02-17-04","vendors": [{"name":"Allora","price":3300,"details":""},{"name":"Asters","price":1999,"details":""},{"name":"Damas Express","price":2595,"details":""}], "resercher": {"title": "އ. ކ. އޮފިސަރ","name": "ޙުސައިން ޝަރީފް"},"sg": {"title": "ކައުންސިލް އެގްޒެކެޓިވް","name": "މުޙައްމަދު ރަބީޢު"},"date":"22/12/2022"},
{"name":"Executive Chair","details":"އެގްޒެކްޓިވް ޗެއަރ އަޅިކުލައިގެ","cat_no":"1.1","ceiling":0.05,"price":1800,"qty":3,"duration":13,"sap_no":"B15-2010-02-17-01","vendors": [{"name":"Allora","price":3300,"details":""},{"name":"Asters","price":1999,"details":""},{"name":"Damas Express","price":2595,"details":""}], "resercher": {"title": "އ. ކ. އޮފިސަރ","name": "ޙުސައިން ޝަރީފް"},"sg": {"title": "ކައުންސިލް އެގްޒެކެޓިވް","name": "މުޙައްމަދު ރަބީޢު"},"date":"22/12/2022"},
{"name":"Executive Chair","details":"އޮފީސް ޗެއަރ ހައިބެކް ލެދަރ","cat_no":"1.1","ceiling":0.05,"price":2500,"qty":2,"duration":6,"sap_no":"B15-2016-02-17-21","vendors": [{"name":"Allora","price":3300,"details":""},{"name":"Asters","price":1999,"details":""},{"name":"Damas Express","price":2595,"details":""}], "resercher": {"title": "އ. ކ. އޮފިސަރ","name": "ޙުސައިން ޝަރީފް"},"sg": {"title": "ކައުންސިލް އެގްޒެކެޓިވް","name": "މުޙައްމަދު ރަބީޢު"},"date":"22/12/2022"},
{"name":"Executive Chair","details":"އޮފީސް ޗެއަރ ހައިބެކް ލެދަރ ( H.L BLACK CL8-001 )","cat_no":"1.1","ceiling":0.05,"price":2846.25,"qty":7,"duration":11,"sap_no":"B15-2011-02-17-14","vendors": [{"name":"Allora","price":3300,"details":""},{"name":"Asters","price":1999,"details":""},{"name":"Damas Express","price":2595,"details":""}], "resercher": {"title": "އ. ކ. އޮފިސަރ","name": "ޙުސައިން ޝަރީފް"},"sg": {"title": "ކައުންސިލް އެގްޒެކެޓިވް","name": "މުޙައްމަދު ރަބީޢު"},"date":"22/12/2022"},
{"name":"Executive Chair","details":"އޮފީސް ޗެއަރ ހައިބެކް ލެދަރ ( MTA 122 )","cat_no":"1.1","ceiling":0.05,"price":5066,"qty":1,"duration":11,"sap_no":"B15-2011-02-17-13","vendors": [{"name":"Allora","price":6614,"details":""},{"name":"Sonee","price":5999,"details":""},{"name":"Damas Express","price":4175,"details":""}], "resercher": {"title": "އ. ކ. އޮފިސަރ","name": "ޙުސައިން ޝަރީފް"},"sg": {"title": "ކައުންސިލް އެގްޒެކެޓިވް","name": "މުޙައްމަދު ރަބީޢު"},"date":"22/12/2022"},
{"name":"Lights / bulbs","details":"މަގުމަތީ ބައްތީގެ ތަންމަތި","cat_no":"1.3","ceiling":0.1,"price":200,"qty":41,"duration":12,"sap_no":"B15-2011-02-37-100","vendors": [{"name":"BuyMore","price":370,"details":""},{"name":"Indiamart","price":112,"details":""},{"name":"Led Tronix","price":175,"details":""}], "resercher": {"title": "އ. ކ. އޮފިސަރ","name": "ޙުސައިން ޝަރީފް"},"sg": {"title": "ކައުންސިލް އެގްޒެކެޓިވް","name": "މުޙައްމަދު ރަބީޢު"},"date":"22/12/2022"},
{"name":"Refrigeretor","details":"މިނީ ފްރިޖު (މިނީ ބާރ، ރެފްރިޖަރޭޓަރ)","cat_no":"2.1","ceiling":0.1,"price":2500,"qty":1,"duration":11,"sap_no":"B15-2012-04-49-01","vendors": [{"name":"Asters","price":2499,"details":""},{"name":"STO","price":2768,"details":""},{"name":"Adman","price":2500,"details":""}], "resercher": {"title": "އ. ކ. އޮފިސަރ","name": "ޙުސައިން ޝަރީފް"},"sg": {"title": "ކައުންސިލް އެގްޒެކެޓިވް","name": "މުޙައްމަދު ރަބީޢު"},"date":"22/12/2022"},
{"name":"Fan","details":"ފަންކާ އުޝާ 12mm","cat_no":"1.3","ceiling":0.1,"price":600,"qty":16,"duration":13,"sap_no":"B15-2010-02-23-01","vendors": [{"name":"Asters","price":699,"details":""},{"name":"Sonee","price":593.4,"details":""},{"name":"Veligaa","price":604.2,"details":""}], "resercher": {"title": "އ. ކ. އޮފިސަރ","name": "ޙުސައިން ޝަރީފް"},"sg": {"title": "ކައުންސިލް އެގްޒެކެޓިވް","name": "މުޙައްމަދު ރަބީޢު"},"date":"22/12/2022"},
{"name":"Fan","details":"ފަންކާ އުޝާ 14mm","cat_no":"1.3","ceiling":0.1,"price":650,"qty":2,"duration":13,"sap_no":"B15-2010-02-23-02","vendors": [{"name":"Asters","price":699,"details":""},{"name":"Sonee","price":593.4,"details":""},{"name":"Veligaa","price":604.2,"details":""}], "resercher": {"title": "އ. ކ. އޮފިސަރ","name": "ޙުސައިން ޝަރީފް"},"sg": {"title": "ކައުންސިލް އެގްޒެކެޓިވް","name": "މުޙައްމަދު ރަބީޢު"},"date":"22/12/2022"},
{"name":"Fan","details":"ފަންކާ ޑިމަރު އުޝާ","cat_no":"1.3","ceiling":0.1,"price":85,"qty":1,"duration":13,"sap_no":"B15-2010-02-22-02","vendors": [{"name":"Asters","price":100,"details":""},{"name":"Sonee","price":125,"details":""},{"name":"Veligaa","price":95,"details":""}], "resercher": {"title": "އ. ކ. އޮފިސަރ","name": "ޙުސައިން ޝަރީފް"},"sg": {"title": "ކައުންސިލް އެގްޒެކެޓިވް","name": "މުޙައްމަދު ރަބީޢު"},"date":"22/12/2022"},
{"name":"Speaker System","details":"ލައުޑް ސްޕީކަރ (ޔުނިޕެކް)","cat_no":"2.3","ceiling":0.5,"price":1800,"qty":3,"duration":13,"sap_no":"B15-2010-04-30-01","vendors": [{"name":"Green Fox Goods","price":1155.729,"details":""},{"name":"PLCCenter","price":1392.426,"details":""},{"name":"Indiamart","price":1895.17,"details":""}], "resercher": {"title": "އ. ކ. އޮފިސަރ","name": "ޙުސައިން ޝަރީފް"},"sg": {"title": "ކައުންސިލް އެގްޒެކެޓިވް","name": "މުޙައްމަދު ރަބީޢު"},"date":"22/12/2022"},
{"name":"Stool Chair","details":"ގޮނޑި ނޫކުލައިގެ(ބަލިމީހުން ނަމާދުކުރާ)","cat_no":"1.1","ceiling":0.1,"price":180,"qty":6,"duration":12,"sap_no":"B15-2011-02-43-01","vendors": [{"name":"eHome","price":230,"details":""},{"name":"DealsHub4u","price":285.76,"details":""},{"name":"Lavish Home","price":416.34,"details":""}], "resercher": {"title": "އ. ކ. އޮފިސަރ","name": "ޙުސައިން ޝަރީފް"},"sg": {"title": "ކައުންސިލް އެގްޒެކެޓިވް","name": "މުޙައްމަދު ރަބީޢު"},"date":"22/12/2022"},
{"name":"Plastic chair","details":"ގޮނޑި ޕްލާސްޓިކް ހުދުކުލައިގެ","cat_no":"1.1","ceiling":0.05,"price":100,"qty":27,"duration":13,"sap_no":"B15-2010-02-29-17","vendors": [{"name":"Asters","price":199,"details":""},{"name":"Sonee","price":233,"details":""},{"name":"Veligaa","price":201.4,"details":""}], "resercher": {"title": "އ. ކ. އޮފިސަރ","name": "ޙުސައިން ޝަރީފް"},"sg": {"title": "ކައުންސިލް އެގްޒެކެޓިވް","name": "މުޙައްމަދު ރަބީޢު"},"date":"22/12/2022"},
{"name":"Fan","details":"ސީލިންގ ފަންކާ ބައިޓަން","cat_no":"1.3","ceiling":0.1,"price":700,"qty":2,"duration":12,"sap_no":"B15-2011-02-23-10","vendors": [{"name":"Asters","price":699,"details":""},{"name":"Sonee","price":593.4,"details":""},{"name":"Veligaa","price":604.2,"details":""}], "resercher": {"title": "އ. ކ. އޮފިސަރ","name": "ޙުސައިން ޝަރީފް"},"sg": {"title": "ކައުންސިލް އެގްޒެކެޓިވް","name": "މުޙައްމަދު ރަބީޢު"},"date":"22/12/2022"},
{"name":"Fan","details":"ސީލިންގ ފަންކާ ކޭޑީކޭ","cat_no":"1.3","ceiling":0.1,"price":800,"qty":1,"duration":12,"sap_no":"B15-2011-02-23-07","vendors": [{"name":"Asters","price":699,"details":""},{"name":"Sonee","price":593.4,"details":""},{"name":"Veligaa","price":604.2,"details":""}], "resercher": {"title": "އ. ކ. އޮފިސަރ","name": "ޙުސައިން ޝަރީފް"},"sg": {"title": "ކައުންސިލް އެގްޒެކެޓިވް","name": "މުޙައްމަދު ރަބީޢު"},"date":"22/12/2022"},
{"name":"Fan","details":"ސްޓޭންޑް ފަންކާ","cat_no":"2.2","ceiling":0.05,"price":1250,"qty":1,"duration":12,"sap_no":"B15-2011-02-23-39","vendors": [{"name":"Asters","price":849,"details":""},{"name":"Sonee","price":1337,"details":""},{"name":"Veligaa","price":1007,"details":""}], "resercher": {"title": "އ. ކ. އޮފިސަރ","name": "ޙުސައިން ޝަރީފް"},"sg": {"title": "ކައުންސިލް އެގްޒެކެޓިވް","name": "މުޙައްމަދު ރަބީޢު"},"date":"22/12/2022"},
{"name":"Desk / Table","details":"ޑެސްކު (ލަކުޑި)","cat_no":"1.1","ceiling":0.1,"price":150,"qty":13,"duration":5,"sap_no":"B15-2018-02-21-07","vendors": [{"name":"Rinkit","price":110.7156,"details":""},{"name":"Texthide-3","price":156.9756,"details":""},{"name":"MHSTARUK","price":172.3956,"details":""}], "resercher": {"title": "އ. ކ. އޮފިސަރ","name": "ޙުސައިން ޝަރީފް"},"sg": {"title": "ކައުންސިލް އެގްޒެކެޓިވް","name": "މުޙައްމަދު ރަބީޢު"},"date":"22/12/2022"}

]}